Workbook

Sheet All Endpoints
A1: Ballys / Bellagio Reservation App – API Endpoints, IIDs and Screens | H1: Total APIs: | I1: =COUNTA(A5:A188)
A2: Source: lib/ folder of ballys-reservation-v2 (branch anu-v6), read on 2026-10-21. IID = value sent as "@Iid" to CommonExecute. "/" separates IIDs picked by tab, type or property. Server names are explained on the "Servers" sheet.
A4: No | B4: Module | C4: Screen | D4: Who Has Access | E4: Screen File(s) | F4: Method | G4: Endpoint | H4: IID | I4: What it does | J4: Code (file → function) | K4: Server | L4: Notes
A5: 1 | B5: Login & App Start | C5: Login, Settings | D5: Anyone (before login) | E5: lib/screens/auth/login_screen.dart lib/screens/settings_screen.dart | F5: POST | G5: Login | H5: — | I5: Get API access token (also used for biometric login) | J5: auth_repository.dart → authenticate() | K5: CRM API
A6: 2 | B6: Login & App Start | C6: Login | D6: Anyone (before login) | E6: lib/screens/auth/login_screen.dart | F6: POST | G6: CommonExecute | H6: 90144 | I6: User login (username / password check) | J6: auth_repository.dart → login() | K6: CRM API
A7: 3 | B7: Login & App Start | C7: OTP Verification, Login | D7: Every user, right after OTP login. Result (ReturnSatetus) = True lets the user open any member on the Members screen | E7: lib/screens/auth/otpVerification_screen.dart lib/screens/auth/login_screen.dart | F7: POST | G7: CommonExecute | H7: 646 | I7: Check whether the user has unrestricted access | J7: auth_repository.dart → fetchAccessStatus() (via auth_provider.completeLoginAfterOTP) | K7: CRM API | L7: Runs right after the OTP login completes
A8: 4 | B8: Login & App Start | C8: Settings | D8: All logged-in users (Settings → Delete Account) | E8: lib/screens/settings_screen.dart | F8: POST | G8: CommonExecute | H8: 90145 | I8: Delete user account | J8: auth_repository.dart → deleteAccount() | K8: CRM API
A9: 5 | B9: Login & App Start | C9: OTP Verification | D9: Anyone logging in (OTP step) | E9: lib/screens/auth/otpVerification_screen.dart | F9: POST | G9: https://api.ballyscolombo.com/api/Ballys/CRM/send-whatsapp | H9: — | I9: Send login OTP by WhatsApp | J9: auth_repository.dart → sendOtpWhatsApp() | K9: Full URL (hard-coded) | L9: URL is hard-coded to Ballys
A10: 6 | B10: Login & App Start | C10: OTP Verification | D10: Anyone logging in (OTP step) | E10: lib/screens/auth/otpVerification_screen.dart | F10: GET | G10: {SMS gateway URL from device config} | H10: — | I10: Send login OTP by SMS | J10: otpVerification_screen.dart → _sendOTPSMS() | K10: SMS Gateway | L10: URL comes from StorageUtil.getSmsGatewayUrl()
A11: 7 | B11: Login & App Start | C11: App Start (Splash), Login | D11: Every device (no login needed) | E11: lib/main.dart lib/screens/auth/login_screen.dart | F11: POST | G11: https://analyticshubapi.bty.world/api/device/log | H11: — | I11: Device config / log – returns the property API URL, SP name, etc. | J11: device_config_service.dart → fetchDeviceConfig() | K11: Device Config API
A12: 8 | B12: Login & App Start | C12: App Start (Splash) | D12: Every device (no login needed) | E12: lib/main.dart | F12: POST | G12: ApiVersion_CRM | H12: Platform 3 = Android, 4 = iOS | I12: App version check / force update | J12: versioncehck_service.dart → checkVersion() | K12: Version Check API | L12: Ballys: https://api.ballyscolombo.com/api/Ballys/ApiVersion_CRM | Bellagio: https://bty.world/api/Bellagio/CRM/ApiVersion_CRM
A13: 9 | B13: Login & App Start | C13: All screens (automatic) | D13: Automatic for any logged-in user | E13: — | F13: POST | G13: Login | H13: — | I13: Refresh expired token (on HTTP 401 / 406 "invalid token") and retry once | J13: token_manager.dart → _doRefresh() | K13: CRM API
A14: 10 | B14: Home | C14: Home (Dashboard) | D14: All logged-in users | E14: lib/screens/home_screen.dart | F14: POST | G14: CommonExecute | H14: 10001 | I14: Get run date (business date) | J14: run_date_repository.dart → getRunDate() | K14: CRM API
A15: 11 | B15: Home | C15: Home (Dashboard) | D15: All logged-in users see the counts. Tapping Today / Yesterday / Monthly: User Level 3 → Access Denied; Level 1 → sales-person breakdown; other levels → member visit list. Data: AD001 can switch to Overall Data (everyone); all others see only their own data (My Data). Opening a member: AD001 = any member; others = only members of their own marketing group | E15: lib/screens/home_screen.dart | F15: POST | G15: CommonExecute | H15: 9009 / 9010 / 9011 | I15: Guest list – 9009 Today, 9010 Yesterday, 9011 Monthly | J15: guest_repository.dart → getGuestData2() (via guests_provider) | K15: CRM API
A16: 12 | B16: Home | C16: Home (Dashboard), Marketing Details | D16: All logged-in users see the card. User Level 3 → Access Denied on tab change and drill-down. Data: AD001 can switch to Overall Data (everyone); all others see only their own data (My Data). Opening a member: AD001 = any member; others = only members of their own marketing group. "Other Marketing": Bellagio AD001 only | E16: lib/screens/home_screen.dart lib/screens/marketing_detail_page.dart | F16: POST | G16: CommonExecute | H16: 8896 / 8897 / 8898 / 8899 | I16: Marketing performance – 8896 Today, 8897 Yesterday, 8898 This Month, 8899 Last Month | J16: marketing_repository.dart → getMarketingData() (via marketing_provider) | K16: CRM API | L16: Home → Marketing Performance card
A17: 13 | B17: Home | C17: Home (Dashboard), Marketing Target Details | D17: All logged-in users see the card. User Level 3 → Access Denied on drill-down. Data: AD001 can switch to Overall Data (everyone); all others see only their own data (My Data). Opening a member: AD001 = any member; others = only members of their own marketing group | E17: lib/screens/home_screen.dart lib/screens/marketing_target_detail_page.dart | F17: POST | G17: CommonExecute | H17: 778898 / 558899 | I17: Marketing target – 778898 Monthly, 558899 Last Month | J17: marketing_repository.dart → getTargetData() | K17: CRM API | L17: Home → Marketing Performance card (Target view)
A18: 14 | B18: Home | C18: Home (Dashboard), Last 3 Months Details | D18: All logged-in users see the card. User Level 3 → Access Denied on refresh / drill-down. Data: AD001 can switch to Overall Data (everyone); all others see only their own data (My Data). Opening a member: AD001 = any member; others = only members of their own marketing group | E18: lib/screens/home_screen.dart lib/screens/last_three_months_detail_page.dart | F18: POST | G18: CommonExecute | H18: 778899 | I18: Last 3 months report | J18: last_three_months_repository.dart → getLastThreeMonthsData() | K18: CRM API | L18: Home → Last 3 Months card
A19: 15 | B19: Home | C19: Home (Dashboard), My Inactive Members, Inactive Members (Main) | D19: Ballys only, not shown to Level 3. Each user sees only their own inactive members (marketing code) | E19: lib/screens/home_screen.dart lib/screens/my_inactive_members_screen.dart lib/screens/Inactive_memberMain.dart | F19: POST | G19: CommonExecute | H19: 885263 | I19: Logged-in user's own inactive members | J19: inactive_members_repository.dart → getMyInactiveMembers() | K19: CRM API | L19: Ballys only. Home shows it as the "My Inactive" banner
A20: 16 | B20: Home | C20: Inactive Members | D20: Menu → Inactive Members (User Level 3 → Access Denied). Ballys: every member returned. Bellagio: AD001 and "MKT CC" see all; others only their own marketing group | E20: lib/screens/inactive_members.dart | F20: POST | G20: CommonExecute | H20: 1059006 (Ballys) / 9006 (Bellagio) | I20: Inactive members list + marketing group summary | J20: inactive_members_repository.dart → getInactiveMembers() | K20: CRM API
A21: 17 | B21: Home | C21: Menu (My Analytics), Reservations (Main), Approvals | D21: All logged-in users (badge counts) | E21: lib/screens/menu_screen.dart lib/screens/reservations/main_reservation.dart lib/screens/approve_reject_show_screen.dart | F21: POST | G21: CommonExecute | H21: 88965 (Ballys) / 8896590 (Bellagio) | I21: Pending approval counts (badges) | J21: pending_repository.dart → getPendingCounts() | K21: CRM API
A22: 18 | B22: Home | C22: Menu (My Analytics), Reservations (Main), Approvals | D22: All logged-in users (badge counts, Ballys only) | E22: lib/screens/menu_screen.dart lib/screens/reservations/main_reservation.dart lib/screens/approve_reject_show_screen.dart | F22: GET | G22: StatusCounts/Get | H22: — | I22: Reservation status counts (badges) | J22: pending_repository.dart → _applyStatusCounts() | K22: CRM API | L22: Ballys only
A23: 19 | B23: Members / Guest | C23: Members, Change Marketer, New Gift Request, New Reservation, New Reservation (Ballys), Quick Reservation, Quick Reservation (Ballys), New Group Reservation, Coordinator Request, Add Transport, Add Transport (Ballys), Add Visa Request | D23: Anyone who can open the host screen (see Screen column). Members screen: Menu → Members (User Level 3 → Access Denied); opening a member: AD001, users with IID 646 = True, or own marketing group only | E23: lib/screens/members_screen.dart lib/screens/change_marketing_person_screen.dart lib/screens/gifts/new_gift_request.dart lib/screens/reservations/new_reservation_screen.dart lib/screens/reservations/new_reservationBallys_screen.dart lib/screens/reservations/quick_reservation_screen.dart lib/screens/reservations/quick_reservation_ballys.dart lib/screens/reservations/group_reservation_ballys_screen.dart lib/screens/reservations/coordinator_request_ballys_screen.dart lib/screens/reservations/transport_add_screen.dart lib/screens/reservations/transport_add_ballys_screen.dart lib/screens/reservations/visa_add_ballys_screen.dart | F23: POST | G23: CommonExecute | H23: 8002 / 8003 | I23: Search member – 8002 by Member ID, 8003 by Name | J23: guest_repository.dart → searchGuest() | K23: CRM API
A24: 20 | B24: Members / Guest | C24: New Reservation, New Reservation (Ballys), Quick Reservation, Quick Reservation (Ballys), Reservation View, Reservation View (Ballys), Add Transport, View Guest Booking, View Special Gift (Check / Approve), View Birthday Gift Request (Check / Approve) | D24: Anyone who can open the host screen (see Screen column) | E24: lib/screens/reservations/new_reservation_screen.dart lib/screens/reservations/new_reservationBallys_screen.dart lib/screens/reservations/quick_reservation_screen.dart lib/screens/reservations/quick_reservation_ballys.dart lib/screens/reservations/reservation_view_screen.dart lib/screens/reservations/reservation_view_screen_ballys.dart lib/screens/reservations/transport_add_screen.dart lib/screens/view_guest_booking.dart lib/screens/gifts/view_special_gift.dart lib/screens/viewBirthdayGiftRequest.dart | F24: POST | G24: CommonExecute | H24: 9021 | I24: Get one member by Member ID (fills the guest card) | J24: guest_repository.dart → searchGuest(9021, mid) | K24: CRM API
A25: 21 | B25: Members / Guest | C25: Marketing Details, Marketing Target Details, Last 3 Months Details, Transport Details, Follow-up Details, View Guest Booking | D25: Opening a member: AD001 = any member; others = only members of their own marketing group (others get Access Denied) | E25: lib/screens/marketing_detail_page.dart lib/screens/marketing_target_detail_page.dart lib/screens/last_three_months_detail_page.dart lib/screens/reservations/transport_view_screen.dart lib/screens/follow_up_view_screen.dart lib/screens/view_guest_booking.dart | F25: POST | G25: CommonExecute | H25: 9021 | I25: Load full guest data by Member ID before opening Guest Profile | J25: guest_repository.dart → getGuestData() (via selected_guest_provider.setSelectedGuestWithId) | K25: CRM API
A26: 22 | B26: Members / Guest | C26: Guest Profile, Member Summary, Trip History, Guest Performance, Gifts, Guest Gifts (Redeem), Birthday Gift Price Increase | D26: Anyone who can open the Guest Profile. Profile rule: AD001 = any member; Mem_Prof_SH true/empty = any member; Mem_Prof_SH false = only own marketing group (or group "W") | E26: lib/screens/profile/profile_screen.dart lib/screens/profile/member_summary_screen.dart lib/screens/profile/trip_history_screen.dart lib/screens/profile/guest_performance/guest_performance_screen.dart lib/screens/gifts/gifts_screen.dart lib/screens/gifts/guest_gifts_screen.dart lib/screens/birthday_gift_price_increase_screen.dart | F26: POST | G26: CommonExecute | H26: 9021 | I26: Get guest photo | J26: guest_repository.dart → fetchGuestImage() | K26: CRM API
A27: 23 | B27: Members / Guest | C27: Follow-up Details, View Guest Booking | D27: Anyone who can open the host screen (see Screen column) | E27: lib/screens/follow_up_view_screen.dart lib/screens/view_guest_booking.dart | F27: POST | G27: CommonExecute | H27: 9022 | I27: Get guest photo (follow-up / booking card) | J27: guest_repository.dart → fetchGuestImage() | K27: CRM API | L27: Same IID 9022 is also used for hotel costs (different screen)
A28: 24 | B28: Members / Guest | C28: Members, Gifts | D28: Menu → Members / Gifts (User Level 3 → Access Denied) | E28: lib/screens/members_screen.dart lib/screens/gifts/gifts_screen.dart | F28: POST | G28: CommonExecute | H28: 9031 | I28: Gift members list | J28: gifts_repository.dart → getGiftMembers() | K28: CRM API
A29: 25 | B29: Members / Guest | C29: Change Marketer | D29: Ballys only. Menu → Members → Change Marketer (User Level 3 → Access Denied) | E29: lib/screens/change_marketing_person_screen.dart | F29: POST | G29: marketer_change_Insert | H29: — | I29: Submit change-marketer request | J29: guest_repository.dart → changeMarketer() | K29: CRM API
A30: 26 | B30: Members / Guest | C30: Marketer Change List | D30: Ballys only. Menu → Members (User Level 3 → Access Denied). AD001 sees all requests; others only their own marketing code | E30: lib/screens/marketer_change_list_screen.dart | F30: GET | G30: GetAllMarketerChange?marketingCodes={code} | H30: — | I30: List marketer change requests (AD001 sees all) | J30: guest_repository.dart → getAllMarketerChanges() | K30: CRM API
A31: 27 | B31: Guest Profile | C31: Guest Profile | D31: Anyone who can open the Guest Profile. Profile rule: AD001 = any member; Mem_Prof_SH true/empty = any member; Mem_Prof_SH false = only own marketing group (or group "W") | E31: lib/screens/profile/profile_screen.dart | F31: POST | G31: CommonExecute | H31: 9030 | I31: Member main profile details | J31: member_profile_repository.dart → getMemberMainProfileDetails() | K31: CRM API
A32: 28 | B32: Guest Profile | C32: Member Summary, Guest Profile | D32: Anyone who can open the Guest Profile. Profile rule: AD001 = any member; Mem_Prof_SH true/empty = any member; Mem_Prof_SH false = only own marketing group (or group "W") | E32: lib/screens/profile/member_summary_screen.dart lib/screens/profile/profile_screen.dart | F32: POST | G32: CommonExecute | H32: 9020 | I32: Member summary | J32: member_profile_repository.dart → getMemberSummary() | K32: CRM API
A33: 29 | B33: Guest Profile | C33: Guest Performance | D33: Anyone who can open the Guest Profile. Profile rule: AD001 = any member; Mem_Prof_SH true/empty = any member; Mem_Prof_SH false = only own marketing group (or group "W") | E33: lib/screens/profile/guest_performance/guest_performance_screen.dart | F33: POST | G33: GetLoyalitySummary | H33: — | I33: Loyalty summary (playerId, DateFrom, DateTo) | J33: member_profile_repository.dart → getLoyalitySummary() | K33: CRM API
A34: 30 | B34: Guest Profile | C34: Guest Performance | D34: Anyone who can open the Guest Profile. Profile rule: AD001 = any member; Mem_Prof_SH true/empty = any member; Mem_Prof_SH false = only own marketing group (or group "W") | E34: lib/screens/profile/guest_performance/guest_performance_screen.dart | F34: POST | G34: GetVisitFrequency | H34: — | I34: Trip information / visit frequency | J34: member_profile_repository.dart → getTripHistory() | K34: CRM API
A35: 31 | B35: Guest Profile | C35: Guest Performance | D35: Anyone who can open the Guest Profile. Profile rule: AD001 = any member; Mem_Prof_SH true/empty = any member; Mem_Prof_SH false = only own marketing group (or group "W") | E35: lib/screens/profile/guest_performance/guest_performance_screen.dart | F35: POST | G35: GetVisitFrequency2 | H35: — | I35: Trip information for a date range | J35: member_profile_repository.dart → getTripHistory2() | K35: CRM API
A36: 32 | B36: Guest Profile | C36: Trip History | D36: Anyone who can open the Guest Profile. Profile rule: AD001 = any member; Mem_Prof_SH true/empty = any member; Mem_Prof_SH false = only own marketing group (or group "W") | E36: lib/screens/profile/trip_history_screen.dart | F36: POST | G36: GetVisitFrequency_V2 | H36: Body "IID": 0 / 1 / 2 | I36: Trip history – 0 Date range, 1 Last 5 trips, 2 Last trip | J36: member_profile_repository.dart → getTripHistory3() | K36: CRM API | L36: IID is sent in the JSON body, not as @Iid
A37: 33 | B37: Guest Profile | C37: Guest Performance | D37: Anyone who can open the Guest Profile. Profile rule: AD001 = any member; Mem_Prof_SH true/empty = any member; Mem_Prof_SH false = only own marketing group (or group "W") | E37: lib/screens/profile/guest_performance/guest_performance_screen.dart | F37: POST | G37: GetTravelHistory | H37: — | I37: Air ticket history (Airlines) | J37: member_profile_repository.dart → getAirlineHistory() | K37: CRM API
A38: 34 | B38: Guest Profile | C38: Guest Performance | D38: Anyone who can open the Guest Profile. Profile rule: AD001 = any member; Mem_Prof_SH true/empty = any member; Mem_Prof_SH false = only own marketing group (or group "W") | E38: lib/screens/profile/guest_performance/guest_performance_screen.dart | F38: POST | G38: GetTravelHistory | H38: — | I38: Hotel reservation history (Hotels) | J38: member_profile_repository.dart → getHotelHistory() | K38: CRM API
A39: 35 | B39: Guest Profile | C39: Guest Performance | D39: Anyone who can open the Guest Profile. Profile rule: AD001 = any member; Mem_Prof_SH true/empty = any member; Mem_Prof_SH false = only own marketing group (or group "W") | E39: lib/screens/profile/guest_performance/guest_performance_screen.dart | F39: POST | G39: GetNonGamingActivities | H39: — | I39: F&B history | J39: member_profile_repository.dart → getFAndBHistory() | K39: CRM API
A40: 36 | B40: Guest Profile | C40: Guest Performance | D40: Anyone who can open the Guest Profile. Profile rule: AD001 = any member; Mem_Prof_SH true/empty = any member; Mem_Prof_SH false = only own marketing group (or group "W") | E40: lib/screens/profile/guest_performance/guest_performance_screen.dart | F40: POST | G40: GetGamingActivities | H40: — | I40: Games summary | J40: member_profile_repository.dart → getGamesSummary() | K40: CRM API
A41: 37 | B41: Guest Profile | C41: Guest Profile | D41: Anyone who can open the Guest Profile. Profile rule: AD001 = any member; Mem_Prof_SH true/empty = any member; Mem_Prof_SH false = only own marketing group (or group "W") | E41: lib/screens/profile/profile_screen.dart | F41: POST | G41: CommonExecute | H41: 8030 / 8031 / 8032 | I41: Add / update phone – 8030 Phone 1, 8031 Phone 2, 8032 Phone 3 | J41: phone_repository.dart → addPhoneNumber() | K41: CRM API | L41: Add Phone dialog
A42: 38 | B42: Guest Profile | C42: Guest Profile | D42: Anyone who can open the Guest Profile. Profile rule: AD001 = any member; Mem_Prof_SH true/empty = any member; Mem_Prof_SH false = only own marketing group (or group "W") | E42: lib/screens/profile/profile_screen.dart | F42: POST | G42: CommonExecute | H42: 8033 / 8034 | I42: Add / update email – 8033 Email 1, 8034 Email 2 | J42: email_repository.dart → addOrUpdateEmail() | K42: CRM API | L42: Add Email dialog
A43: 39 | B43: Guest Profile | C43: Guest Profile | D43: Anyone who can open the Guest Profile. Profile rule: AD001 = any member; Mem_Prof_SH true/empty = any member; Mem_Prof_SH false = only own marketing group (or group "W") | E43: lib/screens/profile/profile_screen.dart | F43: POST | G43: CommonExecute | H43: 8035 / 8036 / 8037 | I43: Add / update WhatsApp – 8035 No 1, 8036 No 2, 8037 No 3 | J43: whatsapp_number_repository.dart → addWhatsAppNumber() | K43: CRM API | L43: Add WhatsApp dialog
A44: 40 | B44: Guest Profile | C44: Guest Profile | D44: Anyone who can open the Guest Profile. Profile rule: AD001 = any member; Mem_Prof_SH true/empty = any member; Mem_Prof_SH false = only own marketing group (or group "W") | E44: lib/screens/profile/profile_screen.dart | F44: POST | G44: CommonExecute | H44: 8038 / 8039 / 8040 | I44: Set primary contact – 8038 Phone, 8039 Email, 8040 WhatsApp | J44: primary_contact_repository.dart → setPrimaryPhone / Email / WhatsApp() | K44: CRM API | L44: Set Primary dialogs
A45: 41 | B45: Guest Profile | C45: Guest Profile, View Special Gift (Check / Approve), View Birthday Gift Request (Check / Approve) | D45: Guest Profile users (profile rule) and gift checkers / approvers on the gift view screens | E45: lib/screens/profile/profile_screen.dart lib/screens/gifts/view_special_gift.dart lib/screens/viewBirthdayGiftRequest.dart | F45: POST | G45: CommonExecute | H45: 8875 | I45: Member's birthday gift details | J45: birthday_gift_repository.dart → getBirthdayGift() | K45: CRM API
A46: 42 | B46: Guest Profile | C46: Guest Profile | D46: Anyone who can open the Guest Profile. Profile rule: AD001 = any member; Mem_Prof_SH true/empty = any member; Mem_Prof_SH false = only own marketing group (or group "W") | E46: lib/screens/profile/profile_screen.dart | F46: POST | G46: https://gift.myanalytics.lk/api/gift/send | H46: — | I46: Send birthday gift WhatsApp message | J46: birthday_repository.dart → sendWhatsappMessage() | K46: Gift WhatsApp API
A47: 43 | B47: Guest Profile | C47: Guest Profile | D47: Anyone who can open the Guest Profile. Profile rule: AD001 = any member; Mem_Prof_SH true/empty = any member; Mem_Prof_SH false = only own marketing group (or group "W") | E47: lib/screens/profile/profile_screen.dart | F47: POST | G47: CommonExecute | H47: 9050 | I47: Save sent-gift record (called right after the WhatsApp send) | J47: birthday_repository.dart → saveGiftData() | K47: CRM API
A48: 44 | B48: Guest Profile | C48: Guest Profile | D48: Anyone who can open the Guest Profile. Profile rule: AD001 = any member; Mem_Prof_SH true/empty = any member; Mem_Prof_SH false = only own marketing group (or group "W") | E48: lib/screens/profile/profile_screen.dart | F48: POST | G48: https://gift.myanalytics.lk/api/gift/otp/send | H48: — | I48: Send normal gift OTP by WhatsApp | J48: gifts_repository.dart → sendNormalGiftWhatsapp() | K48: Gift WhatsApp API
A49: 45 | B49: Other | C49: Birthdays | D49: Menu → Birthdays (User Level 3 → Access Denied). Ballys: every birthday. Bellagio: AD001 all; others only own marketing group | E49: lib/screens/birthday_screen.dart | F49: POST | G49: CommonExecute | H49: 9004 | I49: Birthday list | J49: birthday_repository.dart → getBirthdays() | K49: CRM API
A50: 46 | B50: Other | C50: Daily Walking Guests | D50: Menu → Daily Walking Guests (User Level 3 → Access Denied). Ballys: everyone. Bellagio: AD001 all; others only own marketing group | E50: lib/screens/daily_walking_guests/daily_walking_guests _screen.dart | F50: POST | G50: CommonExecute | H50: 8895 | I50: Daily walking guests list | J50: daily_walking_repository.dart → getAllgest() | K50: CRM API
A51: 47 | B51: Other | C51: Duty Manager | D51: Ballys only. Menu → Duty Manager (User Level 3 → Access Denied) | E51: lib/screens/duty_manager_screen.dart | F51: POST | G51: CommonExecute | H51: 647 | I51: On-duty managers list | J51: duty_manager_repository.dart → getOnDutyManagers() | K51: CRM API
A52: 48 | B52: Other | C52: Academy | D52: Not reachable right now – the Academy menu item is commented out (route /academic still exists) | E52: lib/screens/academic_screen.dart | F52: POST | G52: CommonExecute | H52: 645 | I52: Get Academy web page URL | J52: academic_repository.dart → getAcademicUrl() | K52: CRM API
A53: 49 | B53: Other | C53: Package Guest (Air Tickets) | D53: Menu → Package Guest (User Level 3 → Access Denied) | E53: lib/screens/air_ticket_screen.dart | F53: POST | G53: CommonExecute | H53: 7576 / 7577 | I53: Package guest air tickets – 7576 Recent, 7577 Past | J53: air_ticket_repository.dart → getRecentAirTickets() / getPastAirTickets() | K53: CRM API
A54: 50 | B54: Other | C54: Customer Due Diligence (CDD) | D54: Menu → Members → CDD (User Level 3 → Access Denied) | E54: lib/screens/member_visits/customer_due_diligence_screen.dart | F54: POST | G54: CommonExecute | H54: 10002 | I54: Submit CDD form | J54: customer_due_diligence_repository.dart → submitCDD() | K54: CRM API
A55: 51 | B55: Other | C55: CDD List, Customer Due Diligence (CDD) | D55: Menu → Members → CDD (User Level 3 → Access Denied) | E55: lib/screens/member_visits/cdd_names_screen.dart lib/screens/member_visits/customer_due_diligence_screen.dart | F55: POST | G55: CommonExecute | H55: 10003 | I55: CDD history | J55: customer_due_diligence_repository.dart → fetchCDDHistory() | K55: CRM API
A56: 52 | B56: Other | C56: Guest Bookings, Menu (My Analytics), Chat List, App Start (Splash) | D56: Menu → Guest Bookings (User Level 3 → Access Denied). The menu badge count loads for all users | E56: lib/screens/guest_booking_screen.dart lib/screens/menu_screen.dart lib/screens/chat_screen.dart lib/main.dart | F56: GET | G56: CheckAllBookings | H56: — | I56: Guest bookings list (also menu badge) | J56: guest_booking_repository.dart → getAllBookings() | K56: CRM API
... A69: 65 | B69: Gifts | C69: New Gift Request | D69: Anyone who can open New Gift Request (Gifts / Approvals menu – User Level 3 → Access Denied) | E69: lib/screens/gifts/new_gift_request.dart | F69: POST | G69: CommonExecute | H69: 888999 | I69: Submit new special gift request | J69: gifts_repository.dart → insertSpecialGiftRequest() | K69: CRM API
A70: 66 | B70: Gifts | C70: New Gift Request | D70: Anyone who can open New Gift Request (Gifts / Approvals menu – User Level 3 → Access Denied) | E70: lib/screens/gifts/new_gift_request.dart | F70: POST | G70: CommonExecute | H70: 8889991 | I70: Check if member already has a pending special gift ("Pending Gift Exists" dialog) | J70: new_gift_request.dart → inline call in build() | K70: CRM API | L70: Called directly from the screen, not a repository
A71: 67 | B71: Gifts | C71: View Special Gift (Check / Approve) | D71: G_CHK (special gift checker) – Pending tab | E71: lib/screens/gifts/view_special_gift.dart | F71: POST | G71: CommonExecute | H71: 88794 | I71: Check (verify) special gift request | J71: gifts_repository.dart → checkSpecialGiftRequest() | K71: CRM API
A72: 68 | B72: Gifts | C72: View Special Gift (Check / Approve) | D72: G_App (special gift approver) – Checked tab | E72: lib/screens/gifts/view_special_gift.dart | F72: POST | G72: CommonExecute | H72: 8894 | I72: Approve special gift request | J72: gifts_repository.dart → approvedSPecialgiftRequest() | K72: CRM API
A73: 69 | B73: Gifts | C73: View Special Gift (Check / Approve) | D73: Pending → G_CHK. Checked → G_App | E73: lib/screens/gifts/view_special_gift.dart | F73: POST | G73: CommonExecute | H73: 8892 | I73: Reject special gift request | J73: gifts_repository.dart → rejectSPecialgiftRequest() | K73: CRM API
A74: 70 | B74: Gifts | C74: View Special Gift (Check / Approve) | D74: G_CHK or G_App | E74: lib/screens/gifts/view_special_gift.dart | F74: POST | G74: CommonExecute | H74: 88894 | I74: Reverse special gift request | J74: gifts_repository.dart → reverseSpecialGiftRequest() | K74: CRM API
A75: 71 | B75: Gifts | C75: View Special Gift (Check / Approve) | D75: G_CHK or G_App | E75: lib/screens/gifts/view_special_gift.dart | F75: POST | G75: CommonExecute | H75: 88895 | I75: Reverse a rejected special gift request | J75: gifts_repository.dart → reverseSpecialGiftRequestRejected() | K75: CRM API
A76: 72 | B76: Gifts | C76: View Special Gift (Check / Approve) | D76: Anyone who can open the special gift request | E76: lib/screens/gifts/view_special_gift.dart | F76: POST | G76: https://gift.myanalytics.lk/api/gift/otp/send | H76: — | I76: Send special gift OTP by WhatsApp | J76: gifts_repository.dart → sendSpecialGiftWhatsapp() | K76: Gift WhatsApp API
A77: 73 | B77: Gifts | C77: Birthday Gift Requests, Birthday Gift Price Increase, New Gift Request | D77: Menu → Approvals → Birthday Gifts (User Level 3 → Access Denied). AD001, BG_CHK and BG_APP see all; others only their own requests. Opening follows the same pattern with BG_CHK / BG_APP | E77: lib/screens/birthdayGiftRequestScreen.dart lib/screens/birthday_gift_price_increase_screen.dart lib/screens/gifts/new_gift_request.dart | F77: POST | G77: CommonExecute | H77: 98890 / 788790 / 98891 / 998891 / 98893 | I77: Birthday gift price-increase requests – 98890 Pending, 788790 Checked, 98891 Approved, 998891 Issued, 98893 Rejected | J77: gifts_repository.dart → getBirthdayIncressGift() (via BirthdayGiftIncreesNotifier) | K77: CRM API
A78: 74 | B78: Gifts | C78: Birthday Gift Price Increase | D78: Anyone who can open Birthday Gift Price Increase (Approvals menu – User Level 3 → Access Denied) | E78: lib/screens/birthday_gift_price_increase_screen.dart | F78: POST | G78: CommonExecute | H78: 888998 | I78: Submit birthday gift price-increase request | J78: gifts_repository.dart → increeseBirthdayGiftRequest() | K78: CRM API
A79: 75 | B79: Gifts | C79: Birthday Gift Price Increase, New Gift Request | D79: Anyone who can open Birthday Gift Price Increase (Approvals menu – User Level 3 → Access Denied) | E79: lib/screens/birthday_gift_price_increase_screen.dart lib/screens/gifts/new_gift_request.dart | F79: POST | G79: CommonExecute | H79: 8889992 | I79: Get pending birthday gift ID for a member | J79: gifts_repository.dart → getPendingBirthdayGiftIdByMember() | K79: CRM API
A80: 76 | B80: Gifts | C80: View Birthday Gift Request (Check / Approve) | D80: BG_CHK (birthday gift checker) – Pending tab | E80: lib/screens/viewBirthdayGiftRequest.dart | F80: POST | G80: CommonExecute | H80: 78894 | I80: Check (verify) birthday gift request | J80: gifts_repository.dart → checkbirthdayGiftPriceIncreesRequest() | K80: CRM API
A81: 77 | B81: Gifts | C81: View Birthday Gift Request (Check / Approve) | D81: BG_APP (birthday gift approver) – Checked tab | E81: lib/screens/viewBirthdayGiftRequest.dart | F81: POST | G81: CommonExecute | H81: 98894 | I81: Approve birthday gift request | J81: gifts_repository.dart → approvedBirthdayGiftRequest() | K81: CRM API
A82: 78 | B82: Gifts | C82: View Birthday Gift Request (Check / Approve) | D82: Pending → BG_CHK. Checked → BG_APP | E82: lib/screens/viewBirthdayGiftRequest.dart | F82: POST | G82: CommonExecute | H82: 98892 | I82: Reject birthday gift request | J82: gifts_repository.dart → rejectBirthdayGiftRequest() | K82: CRM API
... A85: 81 | B85: Gifts | C85: View Birthday Gift Request (Check / Approve) | D85: Anyone who can open the birthday gift request | E85: lib/screens/viewBirthdayGiftRequest.dart | F85: POST | G85: https://gift.myanalytics.lk/api/gift/price-increase/send | H85: — | I85: Send birthday price-increase WhatsApp | J85: birthday_repository.dart → sendWhatsappMessagetpPriceincrease() | K85: Gift WhatsApp API
A86: 82 | B86: Gifts | C86: Not used (no screen calls it) | D86: Nobody – not called from any screen | E86: — | F86: POST | G86: CommonExecute | H86: 8889991 | I86: Get special gift by member ID | J86: gifts_repository.dart → getSpecialGiftById() | K86: CRM API | L86: Dead code
A87: 83 | B87: Gifts | C87: Not used (no screen calls it) | D87: Nobody – not called from any screen | E87: — | F87: POST | G87: CommonExecute | H87: 8889991 / 8890 | I87: Get pending gift by member ID | J87: gifts_repository.dart → getPendingGiftByMid() | K87: CRM API | L87: Dead code
A88: 84 | B88: Reservations | C88: Reservations List | D88: Menu → Reservations (User Level 3 → Access Denied). AD001, R_Chk and R_App see every request; others see only their own. Opening: Pending = R_Chk or requester; Checked / Approved = R_App, requester or approver | E88: lib/screens/reservations/reservation_screen.dart | F88: GET | G88: Reservation_GetAllReservations | H88: — | I88: Reservations list | J88: reservation_repository.dart → getReservations() | K88: CRM API
A89: 85 | B89: Reservations | C89: Reservations List (Ballys) | D89: Menu → Reservations (User Level 3 → Access Denied). AD001, R_Chk and R_App see every request; others see only their own. Opening: Pending = R_Chk or requester; Checked / Approved = R_App, requester or approver | E89: lib/screens/reservations/reservation_screen_ballys.dart | F89: GET | G89: Reservation_GetAllReservations | H89: — | I89: Reservations list (Ballys) | J89: reservation_repository.dart → getBallysReservations() | K89: CRM API
A90: 86 | B90: Reservations | C90: New Reservation, New Reservation (Ballys), Quick Reservation, Quick Reservation (Ballys) | D90: Anyone who can open the reservation screens (Menu → Reservations – User Level 3 → Access Denied) | E90: lib/screens/reservations/new_reservation_screen.dart lib/screens/reservations/new_reservationBallys_screen.dart lib/screens/reservations/quick_reservation_screen.dart lib/screens/reservations/quick_reservation_ballys.dart | F90: GET | G90: GetPackageAmounts_MyAnalytics | H90: — | I90: Package amount dropdown | J90: reservation_repository.dart → getPackageAmounts() | K90: CRM API | L90: Bellagio uses MyAnalytics_GetPackageAmounts
A91: 87 | B91: Reservations | C91: New Reservation | D91: Anyone who can open the reservation screens (Menu → Reservations – User Level 3 → Access Denied) | E91: lib/screens/reservations/new_reservation_screen.dart | F91: POST | G91: Reservation_InsertReservation | H91: — | I91: Save new reservation | J91: reservation_repository.dart → saveReservation() | K91: CRM API
A92: 88 | B92: Reservations | C92: New Reservation | D92: Anyone who can open the reservation screens (Menu → Reservations – User Level 3 → Access Denied); the requester edits their own request | E92: lib/screens/reservations/new_reservation_screen.dart | F92: POST | G92: Reservation_InsertReservation | H92: — | I92: Update (edit) reservation | J92: reservation_repository.dart → updateReservation() | K92: CRM API
A93: 89 | B93: Reservations | C93: New Reservation (Ballys) | D93: Anyone who can open the reservation screens (Menu → Reservations – User Level 3 → Access Denied) | E93: lib/screens/reservations/new_reservationBallys_screen.dart | F93: POST | G93: Reservation_InsertReservation | H93: — | I93: Save new reservation (Ballys) | J93: reservation_repository.dart → saveReservationBallys() | K93: CRM API
A94: 90 | B94: Reservations | C94: New Reservation (Ballys) | D94: Anyone who can open the reservation screens (Menu → Reservations – User Level 3 → Access Denied); the requester edits their own request | E94: lib/screens/reservations/new_reservationBallys_screen.dart | F94: POST | G94: Reservation_InsertReservation | H94: — | I94: Update (edit) reservation (Ballys) | J94: reservation_repository.dart → updateReservationBallys() | K94: CRM API
A95: 91 | B95: Reservations | C95: New Reservation (Ballys) | D95: Anyone who can open the reservation screens (Menu → Reservations – User Level 3 → Access Denied) | E95: lib/screens/reservations/new_reservationBallys_screen.dart | F95: POST | G95: Reservation_CheckDuplicate | H95: — | I95: Check duplicate reservation before save | J95: reservation_repository.dart → checkReservationBallys() | K95: CRM API
A96: 92 | B96: Reservations | C96: New Reservation (Ballys) | D96: Anyone who can open the reservation screens (Menu → Reservations – User Level 3 → Access Denied) | E96: lib/screens/reservations/new_reservationBallys_screen.dart | F96: POST | G96: Reservation_InsertAirTicketDuplicate | H96: — | I96: Save "air ticket on the same dates" warnings | J96: reservation_repository.dart → saveAirTicketDuplicateWarnings() | K96: CRM API | L96: Code has TODO: endpoint name to be confirmed with backend
A97: 93 | B97: Reservations | C97: Reservation View | D97: Pending → R_Chk (Check / Reject). Checked → R_App (Approve / Reject). Reverse → R_Chk or R_App | E97: lib/screens/reservations/reservation_view_screen.dart | F97: POST | G97: Reservation_InsertReservation | H97: — | I97: Approve / reject / reverse reservation (re-post with new status) | J97: reservation_repository.dart → updateReservationStatus() | K97: CRM API
A98: 94 | B98: Reservations | C98: Reservation View (Ballys) | D98: Pending → R_Chk (Check / Reject). Checked → R_App (Approve / Reject). Reverse → R_Chk or R_App | E98: lib/screens/reservations/reservation_view_screen_ballys.dart | F98: POST | G98: Reservation_UpdateReservationStatus | H98: — | I98: Approve / reject / reverse reservation (Ballys) | J98: reservation_repository.dart → updateBallysReservationStatus() | K98: CRM API
A99: 95 | B99: Reservations | C99: Reservation View (Ballys) | D99: Anyone who can open an Approved reservation (Amendment button → Payment By) | E99: lib/screens/reservations/reservation_view_screen_ballys.dart | F99: POST | G99: AmendmentPaymentBy/Insert | H99: — | I99: Change "payment by" (amendment) | J99: reservation_repository.dart → submitPaymentByUpdate() | K99: CRM API
A100: 96 | B100: Reservations | C100: Air Ticket Selection, New Reservation (Ballys), Quick Reservation, Quick Reservation (Ballys) | D100: Anyone who can open the reservation screens (Menu → Reservations – User Level 3 → Access Denied) | E100: lib/screens/reservations/air_tickets_selection_screen.dart lib/screens/reservations/new_reservationBallys_screen.dart lib/screens/reservations/quick_reservation_screen.dart lib/screens/reservations/quick_reservation_ballys.dart | F100: POST | G100: CommonExecute | H100: 641 | I100: Contact persons list | J100: contact_person_repository.dart → getContactPersons() | K100: CRM API
A101: 97 | B101: Reservations | C101: New Reservation (Ballys), Quick Reservation (Ballys), Add Transport (Ballys) | D101: Anyone who can open the reservation screens (Menu → Reservations – User Level 3 → Access Denied) | E101: lib/screens/reservations/new_reservationBallys_screen.dart lib/screens/reservations/quick_reservation_ballys.dart lib/screens/reservations/transport_add_ballys_screen.dart | F101: GET | G101: GetAuthorizationLevels | H101: — | I101: Approver / authorization levels | J101: authorization_level_repository.dart → getAuthorizationLevels() | K101: CRM API
A102: 98 | B102: Reservations | C102: Air Ticket Selection, Air Ticket Selection (Ballys), Air Ticket Selection (Ballys, old), Air Ticket Amendment, Quick Reservation, Quick Reservation (Ballys) | D102: Anyone who can open the reservation screens (Menu → Reservations – User Level 3 → Access Denied) | E102: lib/screens/reservations/air_tickets_selection_screen.dart lib/screens/reservations/air_tickets_selection_ballys_screen.dart lib/screens/reservations/air_tickets_selection_screen_ballys.dart lib/screens/reservations/air_ticket_amendment_ballys_screen.dart lib/screens/reservations/quick_reservation_screen.dart lib/screens/reservations/quick_reservation_ballys.dart | F102: POST | G102: CommonExecute | H102: 9018 | I102: Airports list (airport search field) | J102: airport_repository.dart → getAllAirports() (via airports_provider) | K102: CRM API
A103: 99 | B103: Reservations | C103: Air Ticket Selection (Ballys), Quick Reservation (Ballys) | D103: Anyone who can open the reservation screens (Menu → Reservations – User Level 3 → Access Denied) | E103: lib/screens/reservations/air_tickets_selection_ballys_screen.dart lib/screens/reservations/quick_reservation_ballys.dart | F103: POST | G103: CommonExecute | H103: 90156 | I103: Airlines list | J103: airport_repository.dart → getAirlines() | K103: CRM API
A104: 100 | B104: Reservations | C104: Air Ticket Selection, Quick Reservation | D104: Anyone who can open the reservation screens (Menu → Reservations – User Level 3 → Access Denied) | E104: lib/screens/reservations/air_tickets_selection_screen.dart lib/screens/reservations/quick_reservation_screen.dart | F104: POST | G104: CommonExecute | H104: 9023 | I104: Airport / air ticket costs | J104: airport_repository.dart → getAirportCosts() | K104: CRM API
A105: 101 | B105: Reservations | C105: New Reservation, Quick Reservation, Reservation View, Reservation View (Ballys) | D105: Anyone who can open the reservation screens (Menu → Reservations – User Level 3 → Access Denied) | E105: lib/screens/reservations/new_reservation_screen.dart lib/screens/reservations/quick_reservation_screen.dart lib/screens/reservations/reservation_view_screen.dart lib/screens/reservations/reservation_view_screen_ballys.dart | F105: POST | G105: CommonExecute | H105: 9015 | I105: Hotels list | J105: hotel_repository.dart → getAllHotels() (via hotels_provider) | K105: CRM API | L105: airport_repository.dart also has a copy of this call (IID 9015) that nothing uses
A106: 102 | B106: Reservations | C106: New Reservation, Quick Reservation, Air Ticket Selection, Air Ticket Selection (Ballys) | D106: Anyone who can open the reservation screens (Menu → Reservations – User Level 3 → Access Denied) | E106: lib/screens/reservations/new_reservation_screen.dart lib/screens/reservations/quick_reservation_screen.dart lib/screens/reservations/air_tickets_selection_screen.dart lib/screens/reservations/air_tickets_selection_ballys_screen.dart | F106: POST | G106: CommonExecute | H106: 9016 | I106: Hotel room categories | J106: hotel_repository.dart / airport_repository.dart → getSelectedHotelRoomCategories() | K106: CRM API | L106: New Reservation calls it through the Hotel Selection component
A107: 103 | B107: Reservations | C107: New Reservation, Quick Reservation, Air Ticket Selection, Air Ticket Selection (Ballys) | D107: Anyone who can open the reservation screens (Menu → Reservations – User Level 3 → Access Denied) | E107: lib/screens/reservations/new_reservation_screen.dart lib/screens/reservations/quick_reservation_screen.dart lib/screens/reservations/air_tickets_selection_screen.dart lib/screens/reservations/air_tickets_selection_ballys_screen.dart | F107: POST | G107: CommonExecute | H107: 9017 | I107: Hotel room types for a category | J107: hotel_repository.dart / airport_repository.dart → getSelectedHotelCategoryRoomTypes() | K107: CRM API | L107: New Reservation calls it through the Hotel Selection component
A108: 104 | B108: Reservations | C108: New Reservation, New Reservation (Ballys) | D108: Anyone who can open the reservation screens (Menu → Reservations – User Level 3 → Access Denied) | E108: lib/screens/reservations/new_reservation_screen.dart lib/screens/reservations/new_reservationBallys_screen.dart | F108: POST | G108: CommonExecute | H108: 9022 | I108: Hotel costs | J108: hotel_repository.dart → getHotelCosts() | K108: CRM API | L108: Called from Hotel Selection components
A109: 105 | B109: Reservations | C109: New Reservation (Ballys), Hotel Amendment, Quick Reservation (Ballys) | D109: Anyone who can open the reservation screens (Menu → Reservations – User Level 3 → Access Denied) | E109: lib/screens/reservations/new_reservationBallys_screen.dart lib/screens/reservations/hotel_amendment_ballys_screen.dart lib/screens/reservations/quick_reservation_ballys.dart | F109: GET | G109: Hotels/GetByLocationFlat?Location={location} | H109: — | I109: Hotel / room catalog by location | J109: hotel_repository.dart → getHotelRoomCatalog() (via hotel_catalog_provider) | K109: CRM API
A110: 106 | B110: Quick Reservation | C110: Quick Reservation (Ballys) | D110: Menu → Reservations → Quick Reservation (User Level 3 → Access Denied) | E110: lib/screens/reservations/quick_reservation_ballys.dart | F110: POST | G110: Reservation_InsertReservation | H110: — | I110: Quick reservation – save hotel section | J110: quick_reservation_repository.dart → saveHotelReservation() | K110: CRM API
A111: 107 | B111: Quick Reservation | C111: Quick Reservation (Ballys) | D111: Menu → Reservations → Quick Reservation (User Level 3 → Access Denied) | E111: lib/screens/reservations/quick_reservation_ballys.dart | F111: POST | G111: Reservation_InsertReservation | H111: — | I111: Quick reservation – save air ticket section | J111: quick_reservation_repository.dart → saveAirReservation() | K111: CRM API
A112: 108 | B112: Quick Reservation | C112: Quick Reservation (Ballys), Add Transport (Ballys) | D112: Menu → Reservations → Quick Reservation (User Level 3 → Access Denied) or Reservations → Transport (Ballys, User Level 3 → Access Denied) | E112: lib/screens/reservations/quick_reservation_ballys.dart lib/screens/reservations/transport_add_ballys_screen.dart | F112: POST | G112: TransportReservation/Insert | H112: — | I112: Save transport reservation (Ballys) | J112: quick_reservation_repository.dart → saveTransportReservation() | K112: CRM API
A113: 109 | B113: Quick Reservation | C113: Quick Reservation (Ballys), Add Visa Request | D113: Menu → Reservations → Quick Reservation (User Level 3 → Access Denied) or Reservations → Visa (Ballys, User Level 3 → Access Denied) | E113: lib/screens/reservations/quick_reservation_ballys.dart lib/screens/reservations/visa_add_ballys_screen.dart | F113: POST | G113: VisaRequest/Insert | H113: — | I113: Save visa request | J113: quick_reservation_repository.dart → saveVisaRequest() | K113: CRM API
A114: 110 | B114: Quick Reservation | C114: Quick Reservation (Ballys) | D114: Menu → Reservations → Quick Reservation (User Level 3 → Access Denied) | E114: lib/screens/reservations/quick_reservation_ballys.dart | F114: POST | G114: AirportService/Insert | H114: — | I114: Save airport service request | J114: quick_reservation_repository.dart → saveAirportServiceRequest() | K114: CRM API
A115: 111 | B115: Quick Reservation | C115: Quick Reservation | D115: Menu → Reservations → Quick Reservation (User Level 3 → Access Denied) | E115: lib/screens/reservations/quick_reservation_screen.dart | F115: POST | G115: Reservation_InsertReservation | H115: — | I115: Quick reservation – save hotel / air sections | J115: quick_reservation_screen.dart → _saveHotelSection() / _saveAirSection() | K115: CRM API | L115: Called directly from the screen, not a repository
...

Sheet Access Rules
A1: Who has access – how the app decides
A2: All of these come from the login response (IID 90144) and the device config, saved on the phone after OTP. The app checks them on the screen; the server is only asked for a narrower list where noted.
A4: Permission | B4: Login field / source | C4: Value that matters | D4: What it allows | E4: Checked in
A5: Property | B5: Device config → API URL | C5: bty.world = Bellagio, otherwise Ballys | D5: Decides which screens exist. Ballys only: Group Reservation, Amendments, Coordinator, Transport / Visa / Airport Services (Ballys), Duty Manager, Change Marketer, My Inactive Members. Bellagio only: Transport (old) and the per-group filters on Birthdays / Daily Walking / Inactive | E5: menu_screen, main_reservation, membersMainScreen, Inactive_memberMain
A6: User Level | B6: User_Level | C6: 3 | D6: Restricted user. Gets "Access Denied" on: Package Guest, Approvals, Birthdays, Inactive Members, Members, Gifts, Daily Walking, Guest Bookings, Duty Manager; Reservations tiles (Reservations, Quick, Group, Amendments, Transport, Visa, Airport Services); Home count boxes, Marketing and Last 3 Months drill-downs. Can still use Home, Chat, Settings, Coordinator list, Transport (Bellagio) | E6: menu_screen, main_reservation, home_screen, marketing_performance, lastThreemonth
A7: User Level | B7: User_Level | C7: 1 | D7: Home Today / Yesterday / Monthly opens the "All Sales Persons" breakdown instead of a member list | E7: home_screen
A8: Admin sales code | B8: Sales_Code | C8: AD001 | D8: Admin. Overall Data switch, every member profile, every reservation / gift / amendment / transport / group request, every marketer change, share any follow-up PDF. Bellagio: "Other Marketing" group | E8: everywhere (StorageUtil.isAdminSalesCode)
A9: Call-centre code | B9: Sales_Code | C9: MKT CC | D9: Bellagio Inactive Members: sees every member (not just own group) | E9: inactive_members
A10: Marketing group | B10: Marketing_Code | C10: own code (0 = no group) | D10: Non-admin users only see / open members whose group matches this code. Lists from the server are filtered by it (Transport / Visa / Airport / Group / Marketer change). 0 = no "My Data" | E10: members, profile, marketing pages, repositories
A11: Marketing permission | B11: MArketing_P | C11: true | D11: "My Data" is filtered by Marketing_Code instead of Sales_Code | E11: StorageUtil.getDataScopeCode
A12: Member profile access | B12: Mem_Prof_SH | C12: false | D12: Guest Profile opens only for members of the user's own marketing group (or group "W"). true / empty = any member | E12: profile_screen
A13: Unrestricted access | B13: IID 646 → ReturnSatetus | C13: True | D13: Members screen lets the user open any member | E13: members_screen
A14: Reservation checker | B14: R_Chk | C14: true | D14: Sees all reservations, amendments, transport / visa / airport / group requests (Ballys). Check or Reject Pending. Reverse | E14: reservation, amendment, transport, visa, airport, group screens
A15: Reservation approver | B15: R_App | C15: true | D15: Sees all of the above. Approve or Reject Checked. Reverse | E15: same as R_Chk
... A24: Gift_App | B24: Gift_App | C24: — | D24: Saved at login but not checked anywhere in the app | E24: —

Sheet IID List
A1: IID List (CommonExecute "@Iid" values)
A3: IID | B3: What it does | C3: Endpoint | D3: Screen | E3: Who Has Access | F3: Code (file → function) | G3: Row in "All Endpoints"
A4: 641 | B4: Contact persons list | C4: CommonExecute | D4: Air Ticket Selection, New Reservation (Ballys), Quick Reservation, Quick Reservation (Ballys) | E4: Anyone who can open the reservation screens (Menu → Reservations – User Level 3 → Access Denied) | F4: contact_person_repository.dart → getContactPersons() | G4: =HYPERLINK("#'All Endpoints'!A100","Row "&'All Endpoints'!A100)
A5: 645 | B5: Get Academy web page URL | C5: CommonExecute | D5: Academy | E5: Not reachable right now – the Academy menu item is commented out (route /academic still exists) | F5: academic_repository.dart → getAcademicUrl() | G5: =HYPERLINK("#'All Endpoints'!A52","Row "&'All Endpoints'!A52)
A6: 646 | B6: Check whether the user has unrestricted access | C6: CommonExecute | D6: OTP Verification, Login | E6: Every user, right after OTP login. Result (ReturnSatetus) = True lets the user open any member on the Members screen | F6: auth_repository.dart → fetchAccessStatus() (via auth_provider.completeLoginAfterOTP) | G6: =HYPERLINK("#'All Endpoints'!A7","Row "&'All Endpoints'!A7)
A7: 647 | B7: On-duty managers list | C7: CommonExecute | D7: Duty Manager | E7: Ballys only. Menu → Duty Manager (User Level 3 → Access Denied) | F7: duty_manager_repository.dart → getOnDutyManagers() | G7: =HYPERLINK("#'All Endpoints'!A51","Row "&'All Endpoints'!A51)
A8: 7576 | B8: Package guest air tickets – Recent | C8: CommonExecute | D8: Package Guest (Air Tickets) | E8: Menu → Package Guest (User Level 3 → Access Denied) | F8: air_ticket_repository.dart → getRecentAirTickets() / getPastAirTickets() | G8: =HYPERLINK("#'All Endpoints'!A53","Row "&'All Endpoints'!A53)
A9: 7577 | B9: Package guest air tickets – Past | C9: CommonExecute | D9: Package Guest (Air Tickets) | E9: Menu → Package Guest (User Level 3 → Access Denied) | F9: air_ticket_repository.dart → getRecentAirTickets() / getPastAirTickets() | G9: =HYPERLINK("#'All Endpoints'!A53","Row "&'All Endpoints'!A53)
A10: 8002 | B10: Search member – by Member ID | C10: CommonExecute | D10: Members, Change Marketer, New Gift Request, New Reservation, New Reservation (Ballys), Quick Reservation, Quick Reservation (Ballys), New Group Reservation, Coordinator Request, Add Transport, Add Transport (Ballys), Add Visa Request | E10: Anyone who can open the host screen (see Screen column). Members screen: Menu → Members (User Level 3 → Access Denied); opening a member: AD001, users with IID 646 = True, or own marketing group only | F10: guest_repository.dart → searchGuest() | G10: =HYPERLINK("#'All Endpoints'!A23","Row "&'All Endpoints'!A23)
A11: 8003 | B11: Search member – by Name | C11: CommonExecute | D11: Members, Change Marketer, New Gift Request, New Reservation, New Reservation (Ballys), Quick Reservation, Quick Reservation (Ballys), New Group Reservation, Coordinator Request, Add Transport, Add Transport (Ballys), Add Visa Request | E11: Anyone who can open the host screen (see Screen column). Members screen: Menu → Members (User Level 3 → Access Denied); opening a member: AD001, users with IID 646 = True, or own marketing group only | F11: guest_repository.dart → searchGuest() | G11: =HYPERLINK("#'All Endpoints'!A23","Row "&'All Endpoints'!A23)
A12: 8030 | B12: Add / update phone – Phone 1 | C12: CommonExecute | D12: Guest Profile | E12: Anyone who can open the Guest Profile. Profile rule: AD001 = any member; Mem_Prof_SH true/empty = any member; Mem_Prof_SH false = only own marketing group (or group "W") | F12: phone_repository.dart → addPhoneNumber() | G12: =HYPERLINK("#'All Endpoints'!A41","Row "&'All Endpoints'!A41)
A13: 8031 | B13: Add / update phone – Phone 2 | C13: CommonExecute | D13: Guest Profile | E13: Anyone who can open the Guest Profile. Profile rule: AD001 = any member; Mem_Prof_SH true/empty = any member; Mem_Prof_SH false = only own marketing group (or group "W") | F13: phone_repository.dart → addPhoneNumber() | G13: =HYPERLINK("#'All Endpoints'!A41","Row "&'All Endpoints'!A41)
A14: 8032 | B14: Add / update phone – Phone 3 | C14: CommonExecute | D14: Guest Profile | E14: Anyone who can open the Guest Profile. Profile rule: AD001 = any member; Mem_Prof_SH true/empty = any member; Mem_Prof_SH false = only own marketing group (or group "W") | F14: phone_repository.dart → addPhoneNumber() | G14: =HYPERLINK("#'All Endpoints'!A41","Row "&'All Endpoints'!A41)
A15: 8033 | B15: Add / update email – Email 1 | C15: CommonExecute | D15: Guest Profile | E15: Anyone who can open the Guest Profile. Profile rule: AD001 = any member; Mem_Prof_SH true/empty = any member; Mem_Prof_SH false = only own marketing group (or group "W") | F15: email_repository.dart → addOrUpdateEmail() | G15: =HYPERLINK("#'All Endpoints'!A42","Row "&'All Endpoints'!A42)
A16: 8034 | B16: Add / update email – Email 2 | C16: CommonExecute | D16: Guest Profile | E16: Anyone who can open the Guest Profile. Profile rule: AD001 = any member; Mem_Prof_SH true/empty = any member; Mem_Prof_SH false = only own marketing group (or group "W") | F16: email_repository.dart → addOrUpdateEmail() | G16: =HYPERLINK("#'All Endpoints'!A42","Row "&'All Endpoints'!A42)
A17: 8035 | B17: Add / update WhatsApp – No 1 | C17: CommonExecute | D17: Guest Profile | E17: Anyone who can open the Guest Profile. Profile rule: AD001 = any member; Mem_Prof_SH true/empty = any member; Mem_Prof_SH false = only own marketing group (or group "W") | F17: whatsapp_number_repository.dart → addWhatsAppNumber() | G17: =HYPERLINK("#'All Endpoints'!A43","Row "&'All Endpoints'!A43)
A18: 8036 | B18: Add / update WhatsApp – No 2 | C18: CommonExecute | D18: Guest Profile | E18: Anyone who can open the Guest Profile. Profile rule: AD001 = any member; Mem_Prof_SH true/empty = any member; Mem_Prof_SH false = only own marketing group (or group "W") | F18: whatsapp_number_repository.dart → addWhatsAppNumber() | G18: =HYPERLINK("#'All Endpoints'!A43","Row "&'All Endpoints'!A43)
A19: 8037 | B19: Add / update WhatsApp – No 3 | C19: CommonExecute | D19: Guest Profile | E19: Anyone who can open the Guest Profile. Profile rule: AD001 = any member; Mem_Prof_SH true/empty = any member; Mem_Prof_SH false = only own marketing group (or group "W") | F19: whatsapp_number_repository.dart → addWhatsAppNumber() | G19: =HYPERLINK("#'All Endpoints'!A43","Row "&'All Endpoints'!A43)
A20: 8038 | B20: Set primary contact – Phone | C20: CommonExecute | D20: Guest Profile | E20: Anyone who can open the Guest Profile. Profile rule: AD001 = any member; Mem_Prof_SH true/empty = any member; Mem_Prof_SH false = only own marketing group (or group "W") | F20: primary_contact_repository.dart → setPrimaryPhone / Email / WhatsApp() | G20: =HYPERLINK("#'All Endpoints'!A44","Row "&'All Endpoints'!A44)
A21: 8039 | B21: Set primary contact – Email | C21: CommonExecute | D21: Guest Profile | E21: Anyone who can open the Guest Profile. Profile rule: AD001 = any member; Mem_Prof_SH true/empty = any member; Mem_Prof_SH false = only own marketing group (or group "W") | F21: primary_contact_repository.dart → setPrimaryPhone / Email / WhatsApp() | G21: =HYPERLINK("#'All Endpoints'!A44","Row "&'All Endpoints'!A44)
A22: 8040 | B22: Set primary contact – WhatsApp | C22: CommonExecute | D22: Guest Profile | E22: Anyone who can open the Guest Profile. Profile rule: AD001 = any member; Mem_Prof_SH true/empty = any member; Mem_Prof_SH false = only own marketing group (or group "W") | F22: primary_contact_repository.dart → setPrimaryPhone / Email / WhatsApp() | G22: =HYPERLINK("#'All Endpoints'!A44","Row "&'All Endpoints'!A44)
A23: 8875 | B23: Member's birthday gift details | C23: CommonExecute | D23: Guest Profile, View Special Gift (Check / Approve), View Birthday Gift Request (Check / Approve) | E23: Guest Profile users (profile rule) and gift checkers / approvers on the gift view screens | F23: birthday_gift_repository.dart → getBirthdayGift() | G23: =HYPERLINK("#'All Endpoints'!A45","Row "&'All Endpoints'!A45)
A24: 8886 | B24: Guest's gift history for a date range | C24: CommonExecute | D24: New Gift Request, Birthday Gift Price Increase | E24: Anyone who can open New Gift Request (Gifts / Approvals menu – User Level 3 → Access Denied) | F24: gifts_repository.dart → getgestgiftGift() | G24: =HYPERLINK("#'All Endpoints'!A66","Row "&'All Endpoints'!A66)
A25: 8887 | B25: Gift types (gift-for dropdown) | C25: CommonExecute | D25: New Gift Request, Birthday Gift Price Increase, View Special Gift (Check / Approve) | E25: Anyone who can open New Gift Request (Gifts / Approvals menu – User Level 3 → Access Denied) | F25: gifts_repository.dart → getGiftForList() | G25: =HYPERLINK("#'All Endpoints'!A67","Row "&'All Endpoints'!A67)
A26: 8888 | B26: Previous gifts – normal | C26: CommonExecute | D26: Previous Gifts, View Special Gift (Check / Approve), View Birthday Gift Request (Check / Approve) | E26: Anyone who can open the host screen (see Screen column) | F26: gifts_repository.dart → getPrvGiftList() | G26: =HYPERLINK("#'All Endpoints'!A68","Row "&'All Endpoints'!A68)
A27: 8890 | B27: Get pending gift by member ID (not used) | C27: CommonExecute | D27: Not used (no screen calls it) | E27: Nobody – not called from any screen | F27: gifts_repository.dart → getPendingGiftByMid() | G27: =HYPERLINK("#'All Endpoints'!A87","Row "&'All Endpoints'!A87)
A28: 8890 | B28: Special gift requests – Pending | C28: CommonExecute | D28: Special Gift Requests, New Gift Request | E28: Menu → Approvals → Special Gift Requests (User Level 3 → Access Denied). AD001, G_CHK and G_App see all; others only their own requests. Opening: Pending = G_CHK or requester; Checked / Approved = G_App, requester, checker / approver; Issued = G_App, G_CHK or requester; Rejected = requester or rejecter | F28: gifts_repository.dart → getSpecialGift() (via special_gift_provider) | G28: =HYPERLINK("#'All Endpoints'!A65","Row "&'All Endpoints'!A65)
A29: 8891 | B29: Special gift requests – Approved | C29: CommonExecute | D29: Special Gift Requests, New Gift Request | E29: Menu → Approvals → Special Gift Requests (User Level 3 → Access Denied). AD001, G_CHK and G_App see all; others only their own requests. Opening: Pending = G_CHK or requester; Checked / Approved = G_App, requester, checker / approver; Issued = G_App, G_CHK or requester; Rejected = requester or rejecter | F29: gifts_repository.dart → getSpecialGift() (via special_gift_provider) | G29: =HYPERLINK("#'All Endpoints'!A65","Row "&'All Endpoints'!A65)
A30: 8892 | B30: Reject special gift request | C30: CommonExecute | D30: View Special Gift (Check / Approve) | E30: Pending → G_CHK. Checked → G_App | F30: gifts_repository.dart → rejectSPecialgiftRequest() | G30: =HYPERLINK("#'All Endpoints'!A73","Row "&'All Endpoints'!A73)
A31: 8893 | B31: Special gift requests – Rejected | C31: CommonExecute | D31: Special Gift Requests, New Gift Request | E31: Menu → Approvals → Special Gift Requests (User Level 3 → Access Denied). AD001, G_CHK and G_App see all; others only their own requests. Opening: Pending = G_CHK or requester; Checked / Approved = G_App, requester, checker / approver; Issued = G_App, G_CHK or requester; Rejected = requester or rejecter | F31: gifts_repository.dart → getSpecialGift() (via special_gift_provider) | G31: =HYPERLINK("#'All Endpoints'!A65","Row "&'All Endpoints'!A65)
A32: 8894 | B32: Approve special gift request | C32: CommonExecute | D32: View Special Gift (Check / Approve) | E32: G_App (special gift approver) – Checked tab | F32: gifts_repository.dart → approvedSPecialgiftRequest() | G32: =HYPERLINK("#'All Endpoints'!A72","Row "&'All Endpoints'!A72)
A33: 8895 | B33: Daily walking guests list | C33: CommonExecute | D33: Daily Walking Guests | E33: Menu → Daily Walking Guests (User Level 3 → Access Denied). Ballys: everyone. Bellagio: AD001 all; others only own marketing group | F33: daily_walking_repository.dart → getAllgest() | G33: =HYPERLINK("#'All Endpoints'!A50","Row "&'All Endpoints'!A50)
A34: 8896 | B34: Marketing performance – Today | C34: CommonExecute | D34: Home (Dashboard), Marketing Details | E34: All logged-in users see the card. User Level 3 → Access Denied on tab change and drill-down. Data: AD001 can switch to Overall Data (everyone); all others see only their own data (My Data). Opening a member: AD001 = any member; others = only members of their own marketing group. "Other Marketing": Bellagio AD001 only | F34: marketing_repository.dart → getMarketingData() (via marketing_provider) | G34: =HYPERLINK("#'All Endpoints'!A16","Row "&'All Endpoints'!A16)
A35: 8897 | B35: Marketing performance – Yesterday | C35: CommonExecute | D35: Home (Dashboard), Marketing Details | E35: All logged-in users see the card. User Level 3 → Access Denied on tab change and drill-down. Data: AD001 can switch to Overall Data (everyone); all others see only their own data (My Data). Opening a member: AD001 = any member; others = only members of their own marketing group. "Other Marketing": Bellagio AD001 only | F35: marketing_repository.dart → getMarketingData() (via marketing_provider) | G35: =HYPERLINK("#'All Endpoints'!A16","Row "&'All Endpoints'!A16)
A36: 8898 | B36: Marketing performance – This Month | C36: CommonExecute | D36: Home (Dashboard), Marketing Details | E36: All logged-in users see the card. User Level 3 → Access Denied on tab change and drill-down. Data: AD001 can switch to Overall Data (everyone); all others see only their own data (My Data). Opening a member: AD001 = any member; others = only members of their own marketing group. "Other Marketing": Bellagio AD001 only | F36: marketing_repository.dart → getMarketingData() (via marketing_provider) | G36: =HYPERLINK("#'All Endpoints'!A16","Row "&'All Endpoints'!A16)
A37: 8899 | B37: Marketing performance – Last Month | C37: CommonExecute | D37: Home (Dashboard), Marketing Details | E37: All logged-in users see the card. User Level 3 → Access Denied on tab change and drill-down. Data: AD001 can switch to Overall Data (everyone); all others see only their own data (My Data). Opening a member: AD001 = any member; others = only members of their own marketing group. "Other Marketing": Bellagio AD001 only | F37: marketing_repository.dart → getMarketingData() (via marketing_provider) | G37: =HYPERLINK("#'All Endpoints'!A16","Row "&'All Endpoints'!A16)
A38: 9004 | B38: Birthday list | C38: CommonExecute | D38: Birthdays | E38: Menu → Birthdays (User Level 3 → Access Denied). Ballys: every birthday. Bellagio: AD001 all; others only own marketing group | F38: birthday_repository.dart → getBirthdays() | G38: =HYPERLINK("#'All Endpoints'!A49","Row "&'All Endpoints'!A49)
A39: 9006 | B39: Inactive members list + marketing group summary (Bellagio) | C39: CommonExecute | D39: Inactive Members | E39: Menu → Inactive Members (User Level 3 → Access Denied). Ballys: every member returned. Bellagio: AD001 and "MKT CC" see all; others only their own marketing group | F39: inactive_members_repository.dart → getInactiveMembers() | G39: =HYPERLINK("#'All Endpoints'!A20","Row "&'All Endpoints'!A20)
A40: 9009 | B40: Guest list – Today | C40: CommonExecute | D40: Home (Dashboard) | E40: All logged-in users see the counts. Tapping Today / Yesterday / Monthly: User Level 3 → Access Denied; Level 1 → sales-person breakdown; other levels → member visit list. Data: AD001 can switch to Overall Data (everyone); all others see only their own data (My Data). Opening a member: AD001 = any member; others = only members of their own marketing group | F40: guest_repository.dart → getGuestData2() (via guests_provider) | G40: =HYPERLINK("#'All Endpoints'!A15","Row "&'All Endpoints'!A15)
A41: 9010 | B41: Guest list – Yesterday | C41: CommonExecute | D41: Home (Dashboard) | E41: All logged-in users see the counts. Tapping Today / Yesterday / Monthly: User Level 3 → Access Denied; Level 1 → sales-person breakdown; other levels → member visit list. Data: AD001 can switch to Overall Data (everyone); all others see only their own data (My Data). Opening a member: AD001 = any member; others = only members of their own marketing group | F41: guest_repository.dart → getGuestData2() (via guests_provider) | G41: =HYPERLINK("#'All Endpoints'!A15","Row "&'All Endpoints'!A15)
A42: 9011 | B42: Guest list – Monthly | C42: CommonExecute | D42: Home (Dashboard) | E42: All logged-in users see the counts. Tapping Today / Yesterday / Monthly: User Level 3 → Access Denied; Level 1 → sales-person breakdown; other levels → member visit list. Data: AD001 can switch to Overall Data (everyone); all others see only their own data (My Data). Opening a member: AD001 = any member; others = only members of their own marketing group | F42: guest_repository.dart → getGuestData2() (via guests_provider) | G42: =HYPERLINK("#'All Endpoints'!A15","Row "&'All Endpoints'!A15)
A43: 9015 | B43: Hotels list | C43: CommonExecute | D43: New Reservation, Quick Reservation, Reservation View, Reservation View (Ballys) | E43: Anyone who can open the reservation screens (Menu → Reservations – User Level 3 → Access Denied) | F43: hotel_repository.dart → getAllHotels() (via hotels_provider) | G43: =HYPERLINK("#'All Endpoints'!A105","Row "&'All Endpoints'!A105)
A44: 9016 | B44: Hotel room categories | C44: CommonExecute | D44: New Reservation, Quick Reservation, Air Ticket Selection, Air Ticket Selection (Ballys) | E44: Anyone who can open the reservation screens (Menu → Reservations – User Level 3 → Access Denied) | F44: hotel_repository.dart / airport_repository.dart → getSelectedHotelRoomCategories() | G44: =HYPERLINK("#'All Endpoints'!A106","Row "&'All Endpoints'!A106)
A45: 9017 | B45: Hotel room types for a category | C45: CommonExecute | D45: New Reservation, Quick Reservation, Air Ticket Selection, Air Ticket Selection (Ballys) | E45: Anyone who can open the reservation screens (Menu → Reservations – User Level 3 → Access Denied) | F45: hotel_repository.dart / airport_repository.dart → getSelectedHotelCategoryRoomTypes() | G45: =HYPERLINK("#'All Endpoints'!A107","Row "&'All Endpoints'!A107)
A46: 9018 | B46: Airports list (airport search field) | C46: CommonExecute | D46: Air Ticket Selection, Air Ticket Selection (Ballys), Air Ticket Selection (Ballys, old), Air Ticket Amendment, Quick Reservation, Quick Reservation (Ballys) | E46: Anyone who can open the reservation screens (Menu → Reservations – User Level 3 → Access Denied) | F46: airport_repository.dart → getAllAirports() (via airports_provider) | G46: =HYPERLINK("#'All Endpoints'!A102","Row "&'All Endpoints'!A102)
A47: 9020 | B47: Member summary | C47: CommonExecute | D47: Member Summary, Guest Profile | E47: Anyone who can open the Guest Profile. Profile rule: AD001 = any member; Mem_Prof_SH true/empty = any member; Mem_Prof_SH false = only own marketing group (or group "W") | F47: member_profile_repository.dart → getMemberSummary() | G47: =HYPERLINK("#'All Endpoints'!A32","Row "&'All Endpoints'!A32)
A48: 9021 | B48: Get guest photo | C48: CommonExecute | D48: Guest Profile, Member Summary, Trip History, Guest Performance, Gifts, Guest Gifts (Redeem), Birthday Gift Price Increase | E48: Anyone who can open the Guest Profile. Profile rule: AD001 = any member; Mem_Prof_SH true/empty = any member; Mem_Prof_SH false = only own marketing group (or group "W") | F48: guest_repository.dart → fetchGuestImage() | G48: =HYPERLINK("#'All Endpoints'!A26","Row "&'All Endpoints'!A26)
A49: 9021 | B49: Get one member by Member ID (fills the guest card) | C49: CommonExecute | D49: New Reservation, New Reservation (Ballys), Quick Reservation, Quick Reservation (Ballys), Reservation View, Reservation View (Ballys), Add Transport, View Guest Booking, View Special Gift (Check / Approve), View Birthday Gift Request (Check / Approve) | E49: Anyone who can open the host screen (see Screen column) | F49: guest_repository.dart → searchGuest(9021, mid) | G49: =HYPERLINK("#'All Endpoints'!A24","Row "&'All Endpoints'!A24)
A50: 9021 | B50: Load full guest data by Member ID before opening Guest Profile | C50: CommonExecute | D50: Marketing Details, Marketing Target Details, Last 3 Months Details, Transport Details, Follow-up Details, View Guest Booking | E50: Opening a member: AD001 = any member; others = only members of their own marketing group (others get Access Denied) | F50: guest_repository.dart → getGuestData() (via selected_guest_provider.setSelectedGuestWithId) | G50: =HYPERLINK("#'All Endpoints'!A25","Row "&'All Endpoints'!A25)
A51: 9022 | B51: Get guest photo (follow-up / booking card) | C51: CommonExecute | D51: Follow-up Details, View Guest Booking | E51: Anyone who can open the host screen (see Screen column) | F51: guest_repository.dart → fetchGuestImage() | G51: =HYPERLINK("#'All Endpoints'!A27","Row "&'All Endpoints'!A27)
A52: 9022 | B52: Hotel costs | C52: CommonExecute | D52: New Reservation, New Reservation (Ballys) | E52: Anyone who can open the reservation screens (Menu → Reservations – User Level 3 → Access Denied) | F52: hotel_repository.dart → getHotelCosts() | G52: =HYPERLINK("#'All Endpoints'!A108","Row "&'All Endpoints'!A108)
A53: 9023 | B53: Airport / air ticket costs | C53: CommonExecute | D53: Air Ticket Selection, Quick Reservation | E53: Anyone who can open the reservation screens (Menu → Reservations – User Level 3 → Access Denied) | F53: airport_repository.dart → getAirportCosts() | G53: =HYPERLINK("#'All Endpoints'!A104","Row "&'All Endpoints'!A104)
A54: 9030 | B54: Member main profile details | C54: CommonExecute | D54: Guest Profile | E54: Anyone who can open the Guest Profile. Profile rule: AD001 = any member; Mem_Prof_SH true/empty = any member; Mem_Prof_SH false = only own marketing group (or group "W") | F54: member_profile_repository.dart → getMemberMainProfileDetails() | G54: =HYPERLINK("#'All Endpoints'!A31","Row "&'All Endpoints'!A31)
A55: 9031 | B55: Gift members list | C55: CommonExecute | D55: Members, Gifts | E55: Menu → Members / Gifts (User Level 3 → Access Denied) | F55: gifts_repository.dart → getGiftMembers() | G55: =HYPERLINK("#'All Endpoints'!A28","Row "&'All Endpoints'!A28)
A56: 9032 | B56: Guest's gifts | C56: CommonExecute | D56: Guest Gifts (Redeem) | E56: Menu → Gifts (User Level 3 → Access Denied) | F56: gifts_repository.dart → getGuestGifts() | G56: =HYPERLINK("#'All Endpoints'!A62","Row "&'All Endpoints'!A62)
A57: 9050 | B57: Save sent-gift record (called right after the WhatsApp send) | C57: CommonExecute | D57: Guest Profile | E57: Anyone who can open the Guest Profile. Profile rule: AD001 = any member; Mem_Prof_SH true/empty = any member; Mem_Prof_SH false = only own marketing group (or group "W") | F57: birthday_repository.dart → saveGiftData() | G57: =HYPERLINK("#'All Endpoints'!A47","Row "&'All Endpoints'!A47)
A58: 10001 | B58: Get run date (business date) | C58: CommonExecute | D58: Home (Dashboard) | E58: All logged-in users | F58: run_date_repository.dart → getRunDate() | G58: =HYPERLINK("#'All Endpoints'!A14","Row "&'All Endpoints'!A14)
A59: 10002 | B59: Submit CDD form | C59: CommonExecute | D59: Customer Due Diligence (CDD) | E59: Menu → Members → CDD (User Level 3 → Access Denied) | F59: customer_due_diligence_repository.dart → submitCDD() | G59: =HYPERLINK("#'All Endpoints'!A54","Row "&'All Endpoints'!A54)
A60: 10003 | B60: CDD history | C60: CommonExecute | D60: CDD List, Customer Due Diligence (CDD) | E60: Menu → Members → CDD (User Level 3 → Access Denied) | F60: customer_due_diligence_repository.dart → fetchCDDHistory() | G60: =HYPERLINK("#'All Endpoints'!A55","Row "&'All Endpoints'!A55)
A61: 78894 | B61: Check (verify) birthday gift request | C61: CommonExecute | D61: View Birthday Gift Request (Check / Approve) | E61: BG_CHK (birthday gift checker) – Pending tab | F61: gifts_repository.dart → checkbirthdayGiftPriceIncreesRequest() | G61: =HYPERLINK("#'All Endpoints'!A80","Row "&'All Endpoints'!A80)
A62: 88790 | B62: Special gift requests – Checked | C62: CommonExecute | D62: Special Gift Requests, New Gift Request | E62: Menu → Approvals → Special Gift Requests (User Level 3 → Access Denied). AD001, G_CHK and G_App see all; others only their own requests. Opening: Pending = G_CHK or requester; Checked / Approved = G_App, requester, checker / approver; Issued = G_App, G_CHK or requester; Rejected = requester or rejecter | F62: gifts_repository.dart → getSpecialGift() (via special_gift_provider) | G62: =HYPERLINK("#'All Endpoints'!A65","Row "&'All Endpoints'!A65)
A63: 88794 | B63: Check (verify) special gift request | C63: CommonExecute | D63: View Special Gift (Check / Approve) | E63: G_CHK (special gift checker) – Pending tab | F63: gifts_repository.dart → checkSpecialGiftRequest() | G63: =HYPERLINK("#'All Endpoints'!A71","Row "&'All Endpoints'!A71)
A64: 88891 | B64: Special gift requests – Issued | C64: CommonExecute | D64: Special Gift Requests, New Gift Request | E64: Menu → Approvals → Special Gift Requests (User Level 3 → Access Denied). AD001, G_CHK and G_App see all; others only their own requests. Opening: Pending = G_CHK or requester; Checked / Approved = G_App, requester, checker / approver; Issued = G_App, G_CHK or requester; Rejected = requester or rejecter | F64: gifts_repository.dart → getSpecialGift() (via special_gift_provider) | G64: =HYPERLINK("#'All Endpoints'!A65","Row "&'All Endpoints'!A65)
A65: 88894 | B65: Reverse special gift request | C65: CommonExecute | D65: View Special Gift (Check / Approve) | E65: G_CHK or G_App | F65: gifts_repository.dart → reverseSpecialGiftRequest() | G65: =HYPERLINK("#'All Endpoints'!A74","Row "&'All Endpoints'!A74)
A66: 88895 | B66: Reverse a rejected special gift request | C66: CommonExecute | D66: View Special Gift (Check / Approve) | E66: G_CHK or G_App | F66: gifts_repository.dart → reverseSpecialGiftRequestRejected() | G66: =HYPERLINK("#'All Endpoints'!A75","Row "&'All Endpoints'!A75)
A67: 88940 | B67: Previous gifts – for a special gift request | C67: CommonExecute | D67: Previous Gifts, View Special Gift (Check / Approve), View Birthday Gift Request (Check / Approve) | E67: Anyone who can open the host screen (see Screen column) | F67: gifts_repository.dart → getPrvGiftList() | G67: =HYPERLINK("#'All Endpoints'!A68","Row "&'All Endpoints'!A68)
A68: 88965 | B68: Pending approval counts (badges) (Ballys) | C68: CommonExecute | D68: Menu (My Analytics), Reservations (Main), Approvals | E68: All logged-in users (badge counts) | F68: pending_repository.dart → getPendingCounts() | G68: =HYPERLINK("#'All Endpoints'!A21","Row "&'All Endpoints'!A21)
A69: 90144 | B69: User login (username / password check) | C69: CommonExecute | D69: Login | E69: Anyone (before login) | F69: auth_repository.dart → login() | G69: =HYPERLINK("#'All Endpoints'!A6","Row "&'All Endpoints'!A6)
A70: 90145 | B70: Delete user account | C70: CommonExecute | D70: Settings | E70: All logged-in users (Settings → Delete Account) | F70: auth_repository.dart → deleteAccount() | G70: =HYPERLINK("#'All Endpoints'!A8","Row "&'All Endpoints'!A8)
A71: 90156 | B71: Airlines list | C71: CommonExecute | D71: Air Ticket Selection (Ballys), Quick Reservation (Ballys) | E71: Anyone who can open the reservation screens (Menu → Reservations – User Level 3 → Access Denied) | F71: airport_repository.dart → getAirlines() | G71: =HYPERLINK("#'All Endpoints'!A103","Row "&'All Endpoints'!A103)
A72: 90332 | B72: Redeem locations | C72: CommonExecute | D72: Guest Gifts (Redeem) | E72: Menu → Gifts (User Level 3 → Access Denied) | F72: gifts_repository.dart → getRedeemLocations() | G72: =HYPERLINK("#'All Endpoints'!A63","Row "&'All Endpoints'!A63)
A73: 90333 | B73: Redeem a gift | C73: CommonExecute | D73: Guest Gifts (Redeem) | E73: Menu → Gifts (User Level 3 → Access Denied) | F73: gifts_repository.dart → redeemGift() | G73: =HYPERLINK("#'All Endpoints'!A64","Row "&'All Endpoints'!A64)
A74: 98890 | B74: Birthday gift price-increase requests – Pending | C74: CommonExecute | D74: Birthday Gift Requests, Birthday Gift Price Increase, New Gift Request | E74: Menu → Approvals → Birthday Gifts (User Level 3 → Access Denied). AD001, BG_CHK and BG_APP see all; others only their own requests. Opening follows the same pattern with BG_CHK / BG_APP | F74: gifts_repository.dart → getBirthdayIncressGift() (via BirthdayGiftIncreesNotifier) | G74: =HYPERLINK("#'All Endpoints'!A77","Row "&'All Endpoints'!A77)
A75: 98891 | B75: Birthday gift price-increase requests – Approved | C75: CommonExecute | D75: Birthday Gift Requests, Birthday Gift Price Increase, New Gift Request | E75: Menu → Approvals → Birthday Gifts (User Level 3 → Access Denied). AD001, BG_CHK and BG_APP see all; others only their own requests. Opening follows the same pattern with BG_CHK / BG_APP | F75: gifts_repository.dart → getBirthdayIncressGift() (via BirthdayGiftIncreesNotifier) | G75: =HYPERLINK("#'All Endpoints'!A77","Row "&'All Endpoints'!A77)
A76: 98892 | B76: Reject birthday gift request | C76: CommonExecute | D76: View Birthday Gift Request (Check / Approve) | E76: Pending → BG_CHK. Checked → BG_APP | F76: gifts_repository.dart → rejectBirthdayGiftRequest() | G76: =HYPERLINK("#'All Endpoints'!A82","Row "&'All Endpoints'!A82)
A77: 98893 | B77: Birthday gift price-increase requests – Rejected | C77: CommonExecute | D77: Birthday Gift Requests, Birthday Gift Price Increase, New Gift Request | E77: Menu → Approvals → Birthday Gifts (User Level 3 → Access Denied). AD001, BG_CHK and BG_APP see all; others only their own requests. Opening follows the same pattern with BG_CHK / BG_APP | F77: gifts_repository.dart → getBirthdayIncressGift() (via BirthdayGiftIncreesNotifier) | G77: =HYPERLINK("#'All Endpoints'!A77","Row "&'All Endpoints'!A77)
A78: 98894 | B78: Approve birthday gift request | C78: CommonExecute | D78: View Birthday Gift Request (Check / Approve) | E78: BG_APP (birthday gift approver) – Checked tab | F78: gifts_repository.dart → approvedBirthdayGiftRequest() | G78: =HYPERLINK("#'All Endpoints'!A81","Row "&'All Endpoints'!A81)
A79: 558899 | B79: Marketing target – Last Month | C79: CommonExecute | D79: Home (Dashboard), Marketing Target Details | E79: All logged-in users see the card. User Level 3 → Access Denied on drill-down. Data: AD001 can switch to Overall Data (everyone); all others see only their own data (My Data). Opening a member: AD001 = any member; others = only members of their own marketing group | F79: marketing_repository.dart → getTargetData() | G79: =HYPERLINK("#'All Endpoints'!A17","Row "&'All Endpoints'!A17)
A80: 778898 | B80: Marketing target – Monthly | C80: CommonExecute | D80: Home (Dashboard), Marketing Target Details | E80: All logged-in users see the card. User Level 3 → Access Denied on drill-down. Data: AD001 can switch to Overall Data (everyone); all others see only their own data (My Data). Opening a member: AD001 = any member; others = only members of their own marketing group | F80: marketing_repository.dart → getTargetData() | G80: =HYPERLINK("#'All Endpoints'!A17","Row "&'All Endpoints'!A17)
A81: 778899 | B81: Last 3 months report | C81: CommonExecute | D81: Home (Dashboard), Last 3 Months Details | E81: All logged-in users see the card. User Level 3 → Access Denied on refresh / drill-down. Data: AD001 can switch to Overall Data (everyone); all others see only their own data (My Data). Opening a member: AD001 = any member; others = only members of their own marketing group | F81: last_three_months_repository.dart → getLastThreeMonthsData() | G81: =HYPERLINK("#'All Endpoints'!A18","Row "&'All Endpoints'!A18)
A82: 788790 | B82: Birthday gift price-increase requests – Checked | C82: CommonExecute | D82: Birthday Gift Requests, Birthday Gift Price Increase, New Gift Request | E82: Menu → Approvals → Birthday Gifts (User Level 3 → Access Denied). AD001, BG_CHK and BG_APP see all; others only their own requests. Opening follows the same pattern with BG_CHK / BG_APP | F82: gifts_repository.dart → getBirthdayIncressGift() (via BirthdayGiftIncreesNotifier) | G82: =HYPERLINK("#'All Endpoints'!A77","Row "&'All Endpoints'!A77)
A83: 885263 | B83: Logged-in user's own inactive members | C83: CommonExecute | D83: Home (Dashboard), My Inactive Members, Inactive Members (Main) | E83: Ballys only, not shown to Level 3. Each user sees only their own inactive members (marketing code) | F83: inactive_members_repository.dart → getMyInactiveMembers() | G83: =HYPERLINK("#'All Endpoints'!A19","Row "&'All Endpoints'!A19)
A84: 888998 | B84: Submit birthday gift price-increase request | C84: CommonExecute | D84: Birthday Gift Price Increase | E84: Anyone who can open Birthday Gift Price Increase (Approvals menu – User Level 3 → Access Denied) | F84: gifts_repository.dart → increeseBirthdayGiftRequest() | G84: =HYPERLINK("#'All Endpoints'!A78","Row "&'All Endpoints'!A78)
A85: 888999 | B85: Submit new special gift request | C85: CommonExecute | D85: New Gift Request | E85: Anyone who can open New Gift Request (Gifts / Approvals menu – User Level 3 → Access Denied) | F85: gifts_repository.dart → insertSpecialGiftRequest() | G85: =HYPERLINK("#'All Endpoints'!A69","Row "&'All Endpoints'!A69)
A86: 988894 | B86: Reverse birthday gift request | C86: CommonExecute | D86: View Birthday Gift Request (Check / Approve) | E86: BG_CHK or BG_APP | F86: gifts_repository.dart → reverseBirthdayGiftRequest() | G86: =HYPERLINK("#'All Endpoints'!A83","Row "&'All Endpoints'!A83)
A87: 988895 | B87: Reverse a rejected birthday gift request | C87: CommonExecute | D87: View Birthday Gift Request (Check / Approve) | E87: BG_CHK or BG_APP | F87: gifts_repository.dart → reverseBirthdayGiftRequestRejected() | G87: =HYPERLINK("#'All Endpoints'!A84","Row "&'All Endpoints'!A84)
A88: 988908 | B88: Previous gifts – for a birthday gift request | C88: CommonExecute | D88: Previous Gifts, View Special Gift (Check / Approve), View Birthday Gift Request (Check / Approve) | E88: Anyone who can open the host screen (see Screen column) | F88: gifts_repository.dart → getPrvGiftList() | G88: =HYPERLINK("#'All Endpoints'!A68","Row "&'All Endpoints'!A68)
A89: 998891 | B89: Birthday gift price-increase requests – Issued | C89: CommonExecute | D89: Birthday Gift Requests, Birthday Gift Price Increase, New Gift Request | E89: Menu → Approvals → Birthday Gifts (User Level 3 → Access Denied). AD001, BG_CHK and BG_APP see all; others only their own requests. Opening follows the same pattern with BG_CHK / BG_APP | F89: gifts_repository.dart → getBirthdayIncressGift() (via BirthdayGiftIncreesNotifier) | G89: =HYPERLINK("#'All Endpoints'!A77","Row "&'All Endpoints'!A77)
A90: 1059006 | B90: Inactive members list + marketing group summary (Ballys) | C90: CommonExecute | D90: Inactive Members | E90: Menu → Inactive Members (User Level 3 → Access Denied). Ballys: every member returned. Bellagio: AD001 and "MKT CC" see all; others only their own marketing group | F90: inactive_members_repository.dart → getInactiveMembers() | G90: =HYPERLINK("#'All Endpoints'!A20","Row "&'All Endpoints'!A20)
A91: 8889991 | B91: Check if member already has a pending special gift ("Pending Gift Exists" dialog) | C91: CommonExecute | D91: New Gift Request | E91: Anyone who can open New Gift Request (Gifts / Approvals menu – User Level 3 → Access Denied) | F91: new_gift_request.dart → inline call in build() | G91: =HYPERLINK("#'All Endpoints'!A70","Row "&'All Endpoints'!A70)
A92: 8889991 | B92: Get pending gift by member ID (not used) | C92: CommonExecute | D92: Not used (no screen calls it) | E92: Nobody – not called from any screen | F92: gifts_repository.dart → getPendingGiftByMid() | G92: =HYPERLINK("#'All Endpoints'!A87","Row "&'All Endpoints'!A87)
A93: 8889991 | B93: Get special gift by member ID (not used) | C93: CommonExecute | D93: Not used (no screen calls it) | E93: Nobody – not called from any screen | F93: gifts_repository.dart → getSpecialGiftById() | G93: =HYPERLINK("#'All Endpoints'!A86","Row "&'All Endpoints'!A86)
A94: 8889992 | B94: Get pending birthday gift ID for a member | C94: CommonExecute | D94: Birthday Gift Price Increase, New Gift Request | E94: Anyone who can open Birthday Gift Price Increase (Approvals menu – User Level 3 → Access Denied) | F94: gifts_repository.dart → getPendingBirthdayGiftIdByMember() | G94: =HYPERLINK("#'All Endpoints'!A79","Row "&'All Endpoints'!A79)
A95: 8896590 | B95: Pending approval counts (badges) (Bellagio) | C95: CommonExecute | D95: Menu (My Analytics), Reservations (Main), Approvals | E95: All logged-in users (badge counts) | F95: pending_repository.dart → getPendingCounts() | G95: =HYPERLINK("#'All Endpoints'!A21","Row "&'All Endpoints'!A21)

Sheet By Screen
A1: APIs used per screen
A3: Screen | B3: Screen File | C3: No. of APIs | D3: Endpoints (IID) | E3: Who Can Open / Use It
A4: Academy | B4: lib/screens/academic_screen.dart | C4: =COUNTIF('All Endpoints'!E:E,"*"&B4&"*") | D4: • POST CommonExecute [645] – Get Academy web page URL | E4: No menu entry at the moment
A5: Add Follow-up | B5: lib/screens/follow_screen.dart | C5: =COUNTIF('All Endpoints'!E:E,"*"&B5&"*") | D5: • POST followup_Insert – Save a follow-up | E5: Same as Guest Profile
A6: Add Transport | B6: lib/screens/reservations/transport_add_screen.dart | C6: =COUNTIF('All Endpoints'!E:E,"*"&B6&"*") | D6: • POST CommonExecute [8002 / 8003] – Search member – 8002 by Member ID, 8003 by Name • POST CommonExecute [9021] – Get one member by Member ID (fills the guest card) • GET Transport_Get_Data?salesCode={code} – Transport list (admin / approver gets all) • POST Transport_Insert – Add transport • POST v1/places:autocomplete – Place search (new Places API) • GET maps/api/place/autocomplete/json – Place search (legacy fallback) • GET maps/api/geocode/json – Geocode (map pin ↔ address) | E6: Bellagio, all levels
A7: Add Transport (Ballys) | B7: lib/screens/reservations/transport_add_ballys_screen.dart | C7: =COUNTIF('All Endpoints'!E:E,"*"&B7&"*") | D7: • POST CommonExecute [8002 / 8003] – Search member – 8002 by Member ID, 8003 by Name • GET GetAuthorizationLevels – Approver / authorization levels • POST TransportReservation/Insert – Save transport reservation (Ballys) • POST v1/places:autocomplete – Place search (new Places API) • GET maps/api/place/autocomplete/json – Place search (legacy fallback) • GET maps/api/geocode/json – Geocode (map pin ↔ address) | E7: Ballys, not Level 3
A8: Add Visa Request | B8: lib/screens/reservations/visa_add_ballys_screen.dart | C8: =COUNTIF('All Endpoints'!E:E,"*"&B8&"*") | D8: • POST CommonExecute [8002 / 8003] – Search member – 8002 by Member ID, 8003 by Name • POST VisaRequest/Insert – Save visa request | E8: Ballys, not Level 3
A9: Air Ticket Amendment | B9: lib/screens/reservations/air_ticket_amendment_ballys_screen.dart | C9: =COUNTIF('All Endpoints'!E:E,"*"&B9&"*") | D9: • POST CommonExecute [9018] – Airports list (airport search field) • POST AmendmentAir/Insert – Submit air ticket amendment | E9: Anyone viewing an Approved reservation
A10: Air Ticket Selection | B10: lib/screens/reservations/air_tickets_selection_screen.dart | C10: =COUNTIF('All Endpoints'!E:E,"*"&B10&"*") | D10: • POST CommonExecute [641] – Contact persons list • POST CommonExecute [9018] – Airports list (airport search field) • POST CommonExecute [9023] – Airport / air ticket costs • POST CommonExecute [9016] – Hotel room categories • POST CommonExecute [9017] – Hotel room types for a category | E10: Not Level 3
A11: Air Ticket Selection (Ballys) | B11: lib/screens/reservations/air_tickets_selection_ballys_screen.dart | C11: =COUNTIF('All Endpoints'!E:E,"*"&B11&"*") | D11: • POST CommonExecute [9018] – Airports list (airport search field) • POST CommonExecute [90156] – Airlines list • POST CommonExecute [9016] – Hotel room categories • POST CommonExecute [9017] – Hotel room types for a category | E11: Not Level 3
A12: Air Ticket Selection (Ballys, old) | B12: lib/screens/reservations/air_tickets_selection_screen_ballys.dart | C12: =COUNTIF('All Endpoints'!E:E,"*"&B12&"*") | D12: • POST CommonExecute [9018] – Airports list (airport search field) | E12: Not Level 3
A13: Airport Service Details | B13: lib/screens/reservations/airport_service_view_ballys_screen.dart | C13: =COUNTIF('All Endpoints'!E:E,"*"&B13&"*") | D13: • POST AirportService/UpdateStatus – Approve / reject airport service | E13: Pending → R_Chk (Check / Reject). Checked → R_App (Approve / Reject)
A14: Airport Services | B14: lib/screens/reservations/airport_service_ballys_screen.dart | C14: =COUNTIF('All Endpoints'!E:E,"*"&B14&"*") | D14: • GET AirportService/Get?marketingCode={code} – Airport services list | E14: Ballys only, User Level 3 → Access Denied. AD001, R_Chk and R_App see all; others see only their own marketing code
A15: Amendment View (Check / Approve) | B15: lib/screens/reservations/amendment_view_ballys_screen.dart | C15: =COUNTIF('All Endpoints'!E:E,"*"&B15&"*") | D15: • POST {AmendmentAir | AmendmentHotel | AmendmentPaymentBy}/{UpdateChecked | UpdateApproved | UpdateRejected} – Check / approve / reject an amendment | E15: Pending → R_Chk (Check / Reject). Checked → R_App (Approve / Reject)
... A82: Visa Requests | B82: lib/screens/reservations/visa_ballys_screen.dart | C82: =COUNTIF('All Endpoints'!E:E,"*"&B82&"*") | D82: • GET VisaRequest/Get?marketingCode={code} – Visa requests list | E82: Ballys only, User Level 3 → Access Denied. AD001, R_Chk and R_App see all; others see only their own marketing code

Sheet Servers
A1: Servers (base URLs)
A3: Server | B3: Ballys URL | C3: Bellagio URL | D3: How the app picks it | E3: Used by
A4: CRM API | B4: https://api.ballyscolombo.com/api/Ballys/CRM | C4: https://bty.world/api/Bellagio/CRM | D4: StorageUtil.getCurrentApiUrl() – saved from the device config at login. Requests go to {base}/{endpoint} with a Bearer token. | E4: All CommonExecute calls and every other relative endpoint
A5: Chat API | B5: https://chat.bcqr.lk | C5: https://chat.bty.world | D5: FirebaseApiService.resolveDomain() – by logged-in property | E5: Chat, groups, calls, FCM / VoIP tokens
A6: Gift WhatsApp API | B6: https://gift.myanalytics.lk/api | C6: (same) | D6: Constants.laravelAPIbaseUrl | E6: Gift / birthday WhatsApp messages and OTPs
A7: Device Config API | B7: https://analyticshubapi.bty.world/api/device/log | C7: (same) | D7: DeviceConfigService._configApiUrl | E7: App start and login
A8: Version Check API | B8: https://api.ballyscolombo.com/api/Ballys/ApiVersion_CRM | C8: https://bty.world/api/Bellagio/CRM/ApiVersion_CRM | D8: Constants.versionCheckUrl / bellagioVersionCheckUrl | E8: Force-update check at app start
A9: SMS Gateway | B9: (from device config) | C9: (from device config) | D9: StorageUtil.getSmsGatewayUrl() | E9: OTP SMS
A10: Google Maps API | B10: https://places.googleapis.com / https://maps.googleapis.com | C10: (same) | D10: places_service.dart | E10: Location search and map picker
